utility_file_reader/__init__.py
utility_file_reader/reader_utility.py
file_reader_utility-0.5.0.dist-info/LICENSE
file_reader_utility-0.5.0.dist-info/METADATA
file_reader_utility-0.5.0.dist-info/WHEEL
file_reader_utility-0.5.0.dist-info/top_level.txt
file_reader_utility-0.5.0.dist-info/RECORD
