Metadata-Version: 2.1
Name: file-reader-utility
Version: 0.5.0
Summary: file reader utility
Home-page: https://github.com/LahiruMadhawa2020/file-reader-tester.git
Author: Lahiru Madhawa
Author-email: kmlahiru24@gmail.com
License: MIT
Platform: any
Classifier: Development Status :: 2 - Pre-Alpha
Classifier: Intended Audience :: Education
Classifier: Intended Audience :: Developers
Classifier: Intended Audience :: Information Technology
Classifier: Natural Language :: English
Classifier: Programming Language :: Python :: 3
Classifier: License :: OSI Approved :: MIT License
Classifier: Operating System :: OS Independent
Classifier: Programming Language :: Python :: 3.7
Classifier: Programming Language :: Python :: 3.8
Classifier: Topic :: Database
Classifier: Topic :: Database :: Database Engines/Servers
Classifier: Topic :: Software Development :: Libraries :: Python Modules
Requires-Python: >=3.6
License-File: LICENSE
Requires-Dist: setuptools (==60.1.0)
Requires-Dist: wheel (==0.37.1)
Requires-Dist: pytest (==6.1.2)
Requires-Dist: pandas (==1.1.4)
